stock_treemap/__init__.py
stock_treemap-1.6.dist-info/LICENSE
stock_treemap-1.6.dist-info/WHEEL
stock_treemap-1.6.dist-info/METADATA
stock_treemap-1.6.dist-info/RECORD
